dockerdo/__init__.py
dockerdo/config.py
dockerdo/docker.py
dockerdo/dockerdo.bash-completion
dockerdo/dockerdo.py
dockerdo/inotify.py
dockerdo/prettyprint.py
dockerdo/py.typed
dockerdo/shell.py
dockerdo/ssh.py
dockerdo/utils.py
dockerdo-0.3.0.dist-info/entry_points.txt
dockerdo-0.3.0.dist-info/licenses/LICENSE
dockerdo-0.3.0.dist-info/WHEEL
dockerdo-0.3.0.dist-info/METADATA
dockerdo-0.3.0.dist-info/RECORD
