Metadata-Version: 2.4
Name: dockerdo
Version: 0.3.0
Summary: Top-level package for dockerdo.
Author-email: Stig-Arne Grönroos <stig.gronroos@gmail.com>
Requires-Python: >=3.10
License-Expression: MIT
Classifier: Development Status :: 4 - Beta
Classifier: Intended Audience :: Developers
Classifier: Operating System :: POSIX :: Linux
Classifier: Programming Language :: Python
Classifier: Environment :: Console
Classifier: Topic :: Software Development
License-File: LICENSE
Requires-Dist: click>=8.1.8
Requires-Dist: inotify-simple>=1.3.5
Requires-Dist: pydantic>=2.10.6
Requires-Dist: pyyaml>=6.0.2
Requires-Dist: rich>=13.9.4
Project-URL: Documentation, https://dockerdo.readthedocs.io
Project-URL: Source, https://github.com/waino/dockerdo
